LICENSE.txt
MANIFEST.in
README.md
README.txt
requirements.txt
setup.py
REfO.egg-info/PKG-INFO
REfO.egg-info/SOURCES.txt
REfO.egg-info/dependency_links.txt
REfO.egg-info/top_level.txt
examples/path.py
examples/poly_time.py
examples/words.py
examples/xml_reader.py
refo/__init__.py
refo/instructions.py
refo/match.py
refo/patterns.py
refo/virtualmachine.py
tests/test_refo.py