Metadata-Version: 1.1
Name: REfO
Version: 0.13
Summary: Regular expressions for objects
Home-page: https://github.com/machinalis/refo
Author: Rafael Carrascosa
Author-email: rafacarrascosa@gmail.com
License: UNKNOWN
Keywords: regular expressions,regexp,re,objects,classes
Platform: UNKNOWN
Classifier: Programming Language :: Python
Classifier: Development Status :: 3 - Alpha
Classifier: Programming Language :: Python
Classifier: Programming Language :: Python :: 2
Classifier: Programming Language :: Python :: 3
Classifier: Programming Language :: Python :: 2.6
Classifier: Programming Language :: Python :: 2.7
Classifier: Programming Language :: Python :: 3.2
Classifier: Programming Language :: Python :: 3.3
Classifier: Intended Audience :: Developers
Classifier: Natural Language :: English
Classifier: License :: OSI Approved :: BSD License
Classifier: Operating System :: OS Independent
Classifier: Topic :: Scientific/Engineering :: Information Analysis
Classifier: Topic :: Text Processing
Classifier: Topic :: Utilities
